pluginmgr/__init__.py
pluginmgr/config.py
pluginmgr-1.2.1.dist-info/METADATA
pluginmgr-1.2.1.dist-info/WHEEL
pluginmgr-1.2.1.dist-info/licenses/LICENSE
pluginmgr-1.2.1.dist-info/RECORD
