Metadata-Version: 2.3
Name: pluginmgr
Version: 1.2.1
Summary: lightweight python plugin system supporting config inheritance
Project-URL: repository, https://github.com/20c/pluginmgr
Author-email: 20C <code@20c.com>
License: Apache-2.0
License-File: LICENSE
Classifier: Development Status :: 5 - Production/Stable
Classifier: Intended Audience :: Developers
Classifier: License :: OSI Approved :: Apache Software License
Classifier: Programming Language :: Python :: 3.7
Classifier: Programming Language :: Python :: 3.8
Classifier: Programming Language :: Python :: 3.9
Classifier: Programming Language :: Python :: 3.10
Classifier: Programming Language :: Python :: 3.11
Classifier: Programming Language :: Python :: 3.12
Classifier: Topic :: Software Development
Requires-Python: >=3.8
Requires-Dist: importlib-metadata>=1
Requires-Dist: munge>=1
